imongo/__init__.py
imongo/errors.py
imongo/key.py
imongo/model.py
imongo/schema.py
imongo/types.py
imongo/validator/__init__.py
imongo/validator/type_validations.py
imongo/validator/validator.py
tests/__init__.py
tests/conftest.py
tests/core/__init__.py
imongo_orm-0.0.4.dist-info/METADATA
imongo_orm-0.0.4.dist-info/WHEEL
imongo_orm-0.0.4.dist-info/top_level.txt
imongo_orm-0.0.4.dist-info/RECORD
