Metadata-Version: 2.1
Name: imongo-orm
Version: 0.0.4
Summary: MongoDB ORM interface for Python
Home-page: https://github.com/robertocrespond/imongo
Author: Roberto Crespo
Author-email: rcrespoa@alumni.nd.edu
License: UNKNOWN
Keywords: mongo mongodb orm db database document
Platform: UNKNOWN
Classifier: Development Status :: 3 - Alpha
Classifier: Intended Audience :: Developers
Classifier: Topic :: Software Development :: Build Tools
Classifier: License :: OSI Approved :: MIT License
Classifier: Programming Language :: Python :: 3.7
Classifier: Programming Language :: Python :: 3.8
Classifier: Programming Language :: Python :: 3.9
Requires-Dist: wheel
Requires-Dist: pymongo
